{
  "applications": "*",
  "changelogDate": "20231223141305",
  "entityTableName": "student",
  "fields": [
    {
      "fieldName": "number",
      "fieldType": "String",
      "fieldValidateRules": ["required"]
    },
    {
      "fieldName": "cne",
      "fieldType": "String",
      "fieldValidateRules": ["required"]
    },
    {
      "fieldName": "cin",
      "fieldType": "String",
      "fieldValidateRules": ["required"]
    },
    {
      "fieldName": "birthDay",
      "fieldType": "LocalDate",
      "fieldValidateRules": ["required"]
    }
  ],
  "name": "Student",
  "relationships": [
    {
      "otherEntityField": "login",
      "otherEntityName": "user",
      "relationshipName": "user",
      "relationshipSide": "left",
      "relationshipType": "one-to-one",
      "relationshipValidateRules": "required",
      "relationshipWithBuiltInEntity": true
    },
    {
      "otherEntityField": "code",
      "otherEntityName": "groupe",
      "otherEntityRelationshipName": "students",
      "relationshipName": "groupe",
      "relationshipSide": "left",
      "relationshipType": "many-to-one"
    }
  ],
  "searchEngine": "no"
}
